.bandit.yaml
.gitignore
.readthedocs.yml
CODE_OF_CONDUCT.md
CONTRIBUTING.md
LICENSE.rst
MANIFEST.in
README.rst
conftest.py
pyproject.toml
setup.cfg
setup.py
tox.ini
.github/workflows/ci_cron_weekly.yml
.github/workflows/ci_workflows.yml
corazon/__init__.py
corazon/pipeline_search_vet.py
corazon/version.py
corazon.egg-info/PKG-INFO
corazon.egg-info/SOURCES.txt
corazon.egg-info/dependency_links.txt
corazon.egg-info/not-zip-safe
corazon.egg-info/requires.txt
corazon.egg-info/top_level.txt
docs/Makefile
docs/conf.py
docs/index.rst
docs/make.bat
tests/test_pipeline.py