Metadata-Version: 2.1
Name: corazon
Version: 0.0.1a0
Summary: Pipeline to run exovetter
Home-page: https://github.com/spacetelescope/corazon
Author: Susan Mullally et al.
Author-email: smullally@stsci.edu
License: BSD
Keywords: astronomy,astrophysics
Platform: UNKNOWN
Classifier: Intended Audience :: Science/Research
Classifier: License :: OSI Approved :: BSD License
Classifier: Operating System :: OS Independent
Classifier: Programming Language :: Python :: 3
Classifier: Programming Language :: Python :: Implementation :: CPython
Classifier: Topic :: Scientific/Engineering :: Astronomy
Classifier: Topic :: Scientific/Engineering :: Physics
Requires-Python: >=3.7
Provides-Extra: all
Provides-Extra: test
Provides-Extra: docs
